knowde/__init__.py
knowde/complex/__core__/file_io/__init__.py
knowde/complex/__core__/file_io/test_io.py
knowde/complex/__core__/sysnet/__init__.py
knowde/complex/__core__/sysnet/errors.py
knowde/complex/__core__/sysnet/sysfn/__init__.py
knowde/complex/__core__/sysnet/sysfn/build_fn.py
knowde/complex/__core__/sysnet/sysfn/test_sysfn.py
knowde/complex/__core__/sysnet/sysnode/__init__.py
knowde/complex/__core__/sysnet/sysnode/merged_def/__init__.py
knowde/complex/__core__/sysnet/sysnode/merged_def/test_merged_def.py
knowde/complex/__core__/tree2net/__init__.py
knowde/complex/__core__/tree2net/directed_edge.py
knowde/complex/__core__/tree2net/interpreter.py
knowde/complex/__core__/tree2net/lineparse/__init__.py
knowde/complex/__core__/tree2net/lineparse/test_parse_line.py
knowde/complex/__core__/tree2net/meta.py
knowde/complex/__core__/tree2net/test_parse2net.py
knowde/complex/__core__/tree2net/test_regression.py
knowde/complex/__core__/tree2net/transformer.py
knowde/complex/__init__.py
knowde/complex/auth/__init__.py
knowde/complex/auth/errors.py
knowde/complex/auth/manager.py
knowde/complex/auth/repo/__init__.py
knowde/complex/auth/repo/client.py
knowde/complex/auth/repo/test_client.py
knowde/complex/auth/routers.py
knowde/complex/auth/schema.py
knowde/complex/entry/__init__.py
knowde/complex/entry/category/__init__.py
knowde/complex/entry/category/folder/__init__.py
knowde/complex/entry/category/folder/errors.py
knowde/complex/entry/category/folder/repo.py
knowde/complex/entry/category/folder/test_folder.py
knowde/complex/entry/label.py
knowde/complex/entry/repo/__init__.py
knowde/complex/entry/repo/sync.py
knowde/complex/entry/repo/test_namespace.py
knowde/complex/entry/router.py
knowde/complex/nxdb/__init__.py
knowde/complex/nxdb/restore.py
knowde/complex/nxdb/router.py
knowde/complex/nxdb/save.py
knowde/complex/nxdb/test_crud.py
knowde/complex/staging/__init__.py
knowde/complex/staging/test_staging.py
knowde/complex/sysdiff/__init__.py
knowde-0.0.14.dist-info/LICENSE
knowde-0.0.14.dist-info/METADATA
knowde-0.0.14.dist-info/WHEEL
knowde-0.0.14.dist-info/entry_points.txt
knowde-0.0.14.dist-info/RECORD
