Metadata-Version: 2.3
Name: knowde
Version: 0.0.14
Summary: 
Author: Shogo Goto
Author-email: gotoadmn0605@gmail.com
Requires-Python: >3.11.0,<3.14
Classifier: Programming Language :: Python :: 3
Classifier: Programming Language :: Python :: 3.12
Classifier: Programming Language :: Python :: 3.13
Requires-Dist: chardet (>=5.2.0,<6.0.0)
Requires-Dist: click (>=8.1.7,<9.0.0)
Requires-Dist: compose (>=1.5.0,<2.0.0)
Requires-Dist: compose-stubs (>=1.0.0,<2.0.0)
Requires-Dist: edtf (>=5.0.0,<6.0.0)
Requires-Dist: fastapi-users[oauth] (>=14.0.1,<15.0.0)
Requires-Dist: fastapi[standard] (>=0.115.6,<0.116.0)
Requires-Dist: inflector (>=3.1.0,<4.0.0)
Requires-Dist: intervaltree (>=3.1.0,<4.0.0)
Requires-Dist: japanera (>=2.1.2,<3.0.0)
Requires-Dist: lark (>=1.2.2,<2.0.0)
Requires-Dist: levenshtein (>=0.26.1,<0.27.0)
Requires-Dist: makefun (>=1.15.2,<2.0.0)
Requires-Dist: more-itertools (>=10.3.0,<11.0.0)
Requires-Dist: neomodel (==5.4.4)
Requires-Dist: networkx (>=3.2.1,<4.0.0)
Requires-Dist: numpy (>=2.2.2,<3.0.0)
Requires-Dist: pydantic-partial (>=0.5.4,<0.6.0)
Requires-Dist: pydantic-settings (>=2.7.1,<3.0.0)
Requires-Dist: python-multipart (>=0.0.20,<0.0.21)
Requires-Dist: regex (>=2024.11.6,<2025.0.0)
Requires-Dist: requests (>=2.31.0,<3.0.0)
Requires-Dist: scipy (>=1.15.1,<2.0.0)
Requires-Dist: tabulate (>=0.9.0,<0.10.0)
Requires-Dist: taskipy (>=1.14.1,<2.0.0)
Requires-Dist: treelib (>=1.7.0,<2.0.0)
Requires-Dist: uuid6 (>=2023.5.2,<2024.0.0)
Requires-Dist: uvicorn (>=0.24.0.post1,<0.25.0)
Project-URL: Repository, https://github/com/shogogoto/knowde
